{
    "id": 142,
    "name": "Dash",
    "author": "F1regek",
    "creators": [
        "F1regek",
        "XDtheMeme"
    ],
    "verifier": "XDtheMeme",
    "verification": "https://youtu.be/59pZfZ0do2Y",
    "percentToQualify": 100,
    "records": [
        {
            "user": "evil",
            "link": "https://youtu.be/hvK24RoV6bQ",
            "percent": 100,
            "hz": 165
        },
        {
            "user": "Shadow",
            "percent": 100,
            "hz": 60
        },
        {
            "user": "yeckgrinding",
            "link": "https://youtu.be/4egfxGYUUm0",
            "percent": 100,
            "hz": 360
        },
        {
            "user": "pewdiepiereal1",
            "link": "https://youtu.be/HBdQ_WWdiPQ",
            "percent": 100,
            "hz": 165
        },
        {
            "user": "DeepStrider2",
            "percent": 100,
            "hz": 60
        },
        {
            "user": "ZorpikGMD",
            "link": "https://youtu.be/ilHKRRc6TzE?t=283",
            "percent": 100,
            "hz": 240
        },
        {
            "user": "BigRatorBUB",
            "link": "https://imgur.com/hEEZSvR",
            "percent": 100,
            "hz": 240
        },
        {
            "user": "Rin",
            "link": "https://cdn.discordapp.com/attachments/946049906899046401/1113908275969269820/image.png",
            "percent": 100,
            "hz": 360
        },       
        {
            "user": "cinderrblock",
            "link": "https://cdn.discordapp.com/attachments/946049906899046401/1161774205541560390/image.png?ex=6539858b&is=6527108b&hm=77aa9f774cda1ee83db832a0a44d29c7601d6099946e70e373d1e704c1806d8d&",
            "percent": 100,
            "hz": 240
        }
    ]
}
