{
    "id": 490,
    "name": "tick tock",
    "author": "XBladeXGMD",
    "creators": [],
    "verifier": "evil",
    "verification": "https://youtu.be/XIkUgE7EPHE?si=bWBJfwAd-UG5EPyh",
    "percentToQualify": 55,
    "records": [
        {
            "user": "cinderrblock",
            "link": "https://youtu.be/mAjTcp0EYtg?si=JuGWJBuOeXP6qOH3",
            "percent": 100,
            "hz": 240
        },
        {
            "user": "BigRatorBUB",
            "link": "https://youtu.be/6ZVWF34Fs9I?si=CisbgvGLXt_kdCXH",
            "percent": 100,
            "hz": 240
        },
        {
            "user": "Rin",
            "link": "https://youtu.be/gT0gpxYXa6M",
            "percent": 100,
            "hz": 240
        },
        {
            "user": "XBladeXGMD",
            "link": "https://www.youtube.com/watch?v=PZ481XHd1_s",
            "percent": 85,
            "hz": 240
        },
        {
            "user": "syrcx",
            "link": "https://www.youtube.com/watch?v=guiD4kgrSCw",
            "percent": 100,
            "hz": 240
        }
    ]
}
